{
  "config": "{\"version\":\"5.59\",\"themeCollection\":{\"baseTheme\":{\"name\":\"CY24SU10\",\"version\":\"5.62\",\"type\":2}},\"activeSectionIndex\":0,\"defaultDrillFilterOtherVisuals\":true,\"settings\":{\"useNewFilterPaneExperience\":true,\"allowChangeFilterTypes\":true,\"useStylableVisualContainerHeader\":true,\"queryLimitOption\":6,\"useEnhancedTooltips\":true,\"exportDataMode\":1,\"useDefaultAggregateDisplayName\":true},\"objects\":{\"section\":[{\"properties\":{\"verticalAlignment\":{\"expr\":{\"Literal\":{\"Value\":\"'Top'\"}}}}}]}}",
  "layoutOptimization": 0,
  "resourcePackages": [
    {
      "resourcePackage": {
        "disabled": false,
        "items": [
          {
            "name": "CY24SU10",
            "path": "BaseThemes/CY24SU10.json",
            "type": 202
          }
        ],
        "name": "SharedResources",
        "type": 2
      }
    }
  ],
  "sections": [
    {
      "config": "{}",
      "displayName": "Page 1",
      "displayOption": 1,
      "filters": "[]",
      "height": 720.00,
      "name": "cdcaeb8771146173e6ff",
      "visualContainers": [
        {
          "config": "{\"name\":\"7542354d6f0e28a4c3a5\",\"layouts\":[{\"id\":0,\"position\":{\"x\":639.3952973571255,\"y\":14.927516669816159,\"z\":1,\"width\":462.7530167643009,\"height\":364.4801986880112,\"tabOrder\":1}}],\"singleVisual\":{\"visualType\":\"tableEx\",\"projections\":{\"Values\":[{\"queryRef\":\"financials.Product\"},{\"queryRef\":\"financials.Month Name\"},{\"queryRef\":\"Sum(financials. Sales)\"},{\"queryRef\":\"Sum(financials.Profit)\"}]},\"prototypeQuery\":{\"Version\":2,\"From\":[{\"Name\":\"f\",\"Entity\":\"financials\",\"Type\":0}],\"Select\":[{\"Column\":{\"Expression\":{\"SourceRef\":{\"Source\":\"f\"}},\"Property\":\"Product\"},\"Name\":\"financials.Product\",\"NativeReferenceName\":\"Product\"},{\"Column\":{\"Expression\":{\"SourceRef\":{\"Source\":\"f\"}},\"Property\":\"Month Name\"},\"Name\":\"financials.Month Name\",\"NativeReferenceName\":\"Month Name\"},{\"Aggregation\":{\"Expression\":{\"Column\":{\"Expression\":{\"SourceRef\":{\"Source\":\"f\"}},\"Property\":\" Sales\"}},\"Function\":0},\"Name\":\"Sum(financials. Sales)\",\"NativeReferenceName\":\"Sum of  Sales\"},{\"Aggregation\":{\"Expression\":{\"Column\":{\"Expression\":{\"SourceRef\":{\"Source\":\"f\"}},\"Property\":\"Profit\"}},\"Function\":0},\"Name\":\"Sum(financials.Profit)\",\"NativeReferenceName\":\"Sum of Profit\"}]},\"drillFilterOtherVisuals\":true}}",
          "filters": "[]",
          "height": 364.48,
          "width": 462.75,
          "x": 639.40,
          "y": 14.93,
          "z": 1.00
        },
        {
          "config": "{\"name\":\"977bbb3cda4f275490b3\",\"layouts\":[{\"id\":0,\"position\":{\"x\":808.573819615042,\"y\":379.4077153578274,\"z\":2,\"width\":435.38590286963796,\"height\":297.3063736738385,\"tabOrder\":2}}],\"singleVisual\":{\"visualType\":\"pieChart\",\"projections\":{\"Y\":[{\"queryRef\":\"financials.Total_profit\"}],\"Category\":[{\"queryRef\":\"financials.Product\",\"active\":true}]},\"prototypeQuery\":{\"Version\":2,\"From\":[{\"Name\":\"f\",\"Entity\":\"financials\",\"Type\":0}],\"Select\":[{\"Measure\":{\"Expression\":{\"SourceRef\":{\"Source\":\"f\"}},\"Property\":\"Total_profit\"},\"Name\":\"financials.Total_profit\",\"NativeReferenceName\":\"Total_profit\"},{\"Column\":{\"Expression\":{\"SourceRef\":{\"Source\":\"f\"}},\"Property\":\"Product\"},\"Name\":\"financials.Product\",\"NativeReferenceName\":\"Product\"}],\"OrderBy\":[{\"Direction\":2,\"Expression\":{\"Measure\":{\"Expression\":{\"SourceRef\":{\"Source\":\"f\"}},\"Property\":\"Total_profit\"}}}]},\"drillFilterOtherVisuals\":true,\"hasDefaultSort\":true}}",
          "filters": "[]",
          "height": 297.31,
          "width": 435.39,
          "x": 808.57,
          "y": 379.41,
          "z": 2.00
        },
        {
          "config": "{\"name\":\"9b807513cff8c65b4919\",\"layouts\":[{\"id\":0,\"position\":{\"x\":0,\"y\":186.3111111111111,\"z\":0,\"width\":630.0444444444445,\"height\":347.02222222222224,\"tabOrder\":0}}],\"singleVisual\":{\"visualType\":\"clusteredBarChart\",\"projections\":{\"Category\":[{\"queryRef\":\"financials.Country\"}],\"Y\":[{\"queryRef\":\"Sum(financials. Sales)\"}]},\"prototypeQuery\":{\"Version\":2,\"From\":[{\"Name\":\"f\",\"Entity\":\"financials\",\"Type\":0}],\"Select\":[{\"Column\":{\"Expression\":{\"SourceRef\":{\"Source\":\"f\"}},\"Property\":\"Country\"},\"Name\":\"financials.Country\",\"NativeReferenceName\":\"Country\"},{\"Aggregation\":{\"Expression\":{\"Column\":{\"Expression\":{\"SourceRef\":{\"Source\":\"f\"}},\"Property\":\" Sales\"}},\"Function\":0},\"Name\":\"Sum(financials. Sales)\",\"NativeReferenceName\":\"Sum of  Sales\"}],\"OrderBy\":[{\"Direction\":2,\"Expression\":{\"Aggregation\":{\"Expression\":{\"Column\":{\"Expression\":{\"SourceRef\":{\"Source\":\"f\"}},\"Property\":\" Sales\"}},\"Function\":0}}}]},\"drillFilterOtherVisuals\":true,\"objects\":{\"dataPoint\":[{\"properties\":{\"fill\":{\"solid\":{\"color\":{\"expr\":{\"ThemeDataColor\":{\"ColorId\":5,\"Percent\":-0.25}}}}}}}]}}}",
          "filters": "[]",
          "height": 347.02,
          "width": 630.04,
          "x": 0.00,
          "y": 186.31,
          "z": 0.00
        }
      ],
      "width": 1280.00
    }
  ]
}